{
  "dependencies": {
    "lodash": "registry:npm/lodash#4.0.0+20160416211519",
    "mongoose": "registry:npm/mongoose#4.3.5+20160610145311"
  },
  "globalDependencies": {
    "deep-diff": "registry:dt/deep-diff#0.0.0+20160317120654",
    "node": "registry:dt/node#6.0.0+20160608110640"
  },
  "globalDevDependencies": {
    "expect.js": "registry:dt/expect.js#0.3.1+20160317120654",
    "mocha": "registry:dt/mocha#2.2.5+20160317120654"
  },
  "devDependencies": {
    "sinon": "registry:npm/sinon#1.16.0+20160427193336"
  }
}
